{
  "parent": "create:linked_controller",
  "criteria": {
    "0": {
      "conditions": {},
      "trigger": "create:arm_blaze_burner_builtin"
    }
  },
  "display": {
    "announce_to_chat": false,
    "description": {
      "color": "#DBA213",
      "translate": "advancement.create.arm_blaze_burner.desc"
    },
    "frame": "task",
    "hidden": false,
    "icon": {
      "item": "create:blaze_burner"
    },
    "show_toast": true,
    "title": {
      "translate": "advancement.create.arm_blaze_burner"
    }
  },
  "requirements": [
    [
      "0"
    ]
  ]
}